{
  "updatedAt": "2025-12-22T14:52:00.720Z",
  "year": 2027,
  "events": [
    {
      "date": "2027-01-01",
      "id": "shabbat",
      "requiresAlert": true,
      "isSecondDay": false,
      "name": "שבת פרשת שמות",
      "type": "SHABBAT"
    },
    {
      "date": "2027-01-08",
      "requiresAlert": true,
      "id": "shabbat",
      "type": "SHABBAT",
      "name": "שבת פרשת וארא",
      "isSecondDay": false
    },
    {
      "requiresAlert": true,
      "isSecondDay": false,
      "type": "SHABBAT",
      "name": "שבת פרשת בא",
      "id": "shabbat",
      "date": "2027-01-15"
    },
    {
      "date": "2027-01-22",
      "isSecondDay": false,
      "name": "שבת פרשת בשלח",
      "requiresAlert": true,
      "id": "shabbat",
      "type": "SHABBAT"
    },
    {
      "requiresAlert": true,
      "isSecondDay": false,
      "name": "שבת פרשת יתרו",
      "date": "2027-01-29",
      "id": "shabbat",
      "type": "SHABBAT"
    },
    {
      "name": "שבת פרשת משפטים",
      "requiresAlert": true,
      "type": "SHABBAT",
      "isSecondDay": false,
      "date": "2027-02-05",
      "id": "shabbat"
    },
    {
      "isSecondDay": false,
      "id": "shabbat",
      "date": "2027-02-12",
      "requiresAlert": true,
      "name": "שבת פרשת תרומה",
      "type": "SHABBAT"
    },
    {
      "id": "shabbat",
      "type": "SHABBAT",
      "name": "שבת פרשת תצוה",
      "isSecondDay": false,
      "requiresAlert": true,
      "date": "2027-02-19"
    },
    {
      "requiresAlert": false,
      "id": "Purim_Katan",
      "type": "HOLIDAY",
      "isSecondDay": false,
      "name": "Purim Katan",
      "date": "2027-02-20"
    },
    {
      "type": "HOLIDAY",
      "name": "Shushan Purim Katan",
      "isSecondDay": false,
      "id": "Shushan_Purim_Katan",
      "requiresAlert": false,
      "date": "2027-02-21"
    },
    {
      "name": "שבת פרשת כי תשא",
      "requiresAlert": true,
      "date": "2027-02-26",
      "type": "SHABBAT",
      "isSecondDay": false,
      "id": "shabbat"
    },
    {
      "date": "2027-03-05",
      "type": "SHABBAT",
      "name": "שבת פרשת ויקהל",
      "requiresAlert": true,
      "isSecondDay": false,
      "id": "shabbat"
    },
    {
      "requiresAlert": true,
      "type": "SHABBAT",
      "date": "2027-03-12",
      "isSecondDay": false,
      "name": "שבת פרשת פקודי",
      "id": "shabbat"
    },
    {
      "requiresAlert": true,
      "id": "shabbat",
      "isSecondDay": false,
      "type": "SHABBAT",
      "date": "2027-03-19",
      "name": "שבת פרשת ויקרא"
    },
    {
      "id": "פורים",
      "isSecondDay": false,
      "type": "HOLIDAY",
      "name": "פורים",
      "date": "2027-03-22",
      "requiresAlert": false
    },
    {
      "requiresAlert": false,
      "date": "2027-03-23",
      "name": "שושן פורים",
      "type": "HOLIDAY",
      "isSecondDay": false,
      "id": "שושן_פורים"
    },
    {
      "type": "SHABBAT",
      "id": "shabbat",
      "date": "2027-03-26",
      "isSecondDay": false,
      "name": "שבת פרשת צו",
      "requiresAlert": true
    },
    {
      "isSecondDay": false,
      "type": "SHABBAT",
      "date": "2027-04-02",
      "requiresAlert": true,
      "name": "שבת פרשת שמיני",
      "id": "shabbat"
    },
    {
      "type": "SHABBAT",
      "id": "shabbat",
      "isSecondDay": false,
      "name": "שבת פרשת תזריע",
      "requiresAlert": true,
      "date": "2027-04-09"
    },
    {
      "name": "שבת פרשת מצרע",
      "isSecondDay": false,
      "date": "2027-04-16",
      "requiresAlert": true,
      "id": "shabbat",
      "type": "SHABBAT"
    },
    {
      "requiresAlert": true,
      "type": "HOLIDAY",
      "isSecondDay": false,
      "name": "חג הפסח (ליל הסדר)",
      "date": "2027-04-21",
      "id": "חג_הפסח_(ליל_הסדר)"
    },
    {
      "isSecondDay": false,
      "type": "HOLIDAY",
      "requiresAlert": false,
      "id": "Pesach_II",
      "date": "2027-04-22",
      "name": "Pesach II"
    },
    {
      "date": "2027-04-23",
      "requiresAlert": true,
      "name": "שבת - חול המועד פסח",
      "id": "שבת_-_חול_המועד_פסח",
      "isSecondDay": false,
      "type": "HOLIDAY"
    },
    {
      "date": "2027-04-24",
      "requiresAlert": false,
      "type": "HOLIDAY",
      "name": "חול המועד פסח",
      "id": "חול_המועד_פסח",
      "isSecondDay": false
    },
    {
      "date": "2027-04-25",
      "name": "חול המועד פסח",
      "type": "HOLIDAY",
      "isSecondDay": false,
      "requiresAlert": false,
      "id": "חול_המועד_פסח"
    },
    {
      "name": "חול המועד פסח",
      "id": "חול_המועד_פסח",
      "isSecondDay": false,
      "date": "2027-04-26",
      "requiresAlert": false,
      "type": "HOLIDAY"
    },
    {
      "requiresAlert": true,
      "isSecondDay": false,
      "type": "HOLIDAY",
      "id": "שביעי_של_פסח",
      "date": "2027-04-27",
      "name": "שביעי של פסח"
    },
    {
      "name": "שבת פרשת אחרי מות",
      "id": "shabbat",
      "date": "2027-04-30",
      "requiresAlert": true,
      "isSecondDay": false,
      "type": "SHABBAT"
    },
    {
      "type": "SHABBAT",
      "id": "shabbat",
      "date": "2027-05-07",
      "requiresAlert": true,
      "name": "שבת פרשת קדשים",
      "isSecondDay": false
    },
    {
      "requiresAlert": true,
      "id": "shabbat",
      "isSecondDay": false,
      "type": "SHABBAT",
      "name": "שבת פרשת אמור",
      "date": "2027-05-14"
    },
    {
      "isSecondDay": false,
      "id": "shabbat",
      "name": "שבת פרשת בהר",
      "requiresAlert": true,
      "date": "2027-05-21",
      "type": "SHABBAT"
    },
    {
      "date": "2027-05-28",
      "id": "shabbat",
      "name": "שבת פרשת בחקתי",
      "isSecondDay": false,
      "requiresAlert": true,
      "type": "SHABBAT"
    },
    {
      "date": "2027-06-04",
      "isSecondDay": false,
      "name": "שבת פרשת במדבר",
      "type": "SHABBAT",
      "id": "shabbat",
      "requiresAlert": true
    },
    {
      "type": "HOLIDAY",
      "name": "חג השבועות",
      "isSecondDay": false,
      "requiresAlert": true,
      "date": "2027-06-10",
      "id": "חג_השבועות"
    },
    {
      "name": "שבת - Shavuot II",
      "type": "SHABBAT",
      "isSecondDay": true,
      "id": "שבת_-_Shavuot_II",
      "date": "2027-06-11",
      "requiresAlert": false
    },
    {
      "requiresAlert": true,
      "id": "shabbat",
      "date": "2027-06-18",
      "type": "SHABBAT",
      "isSecondDay": false,
      "name": "שבת פרשת נשא"
    },
    {
      "name": "שבת פרשת בהעלתך",
      "isSecondDay": false,
      "id": "shabbat",
      "date": "2027-06-25",
      "type": "SHABBAT",
      "requiresAlert": true
    },
    {
      "isSecondDay": false,
      "id": "shabbat",
      "name": "שבת פרשת שלח־לך",
      "type": "SHABBAT",
      "date": "2027-07-02",
      "requiresAlert": true
    },
    {
      "type": "SHABBAT",
      "name": "שבת פרשת קורח",
      "isSecondDay": false,
      "date": "2027-07-09",
      "requiresAlert": true,
      "id": "shabbat"
    },
    {
      "name": "שבת פרשת חוקת-בלק",
      "id": "shabbat",
      "type": "SHABBAT",
      "isSecondDay": false,
      "requiresAlert": true,
      "date": "2027-07-16"
    },
    {
      "requiresAlert": true,
      "date": "2027-07-23",
      "type": "SHABBAT",
      "name": "שבת פרשת פינחס",
      "isSecondDay": false,
      "id": "shabbat"
    },
    {
      "id": "shabbat",
      "type": "SHABBAT",
      "name": "שבת פרשת מטות-מסעי",
      "requiresAlert": true,
      "isSecondDay": false,
      "date": "2027-07-30"
    },
    {
      "id": "shabbat",
      "name": "שבת פרשת דברים",
      "type": "SHABBAT",
      "isSecondDay": false,
      "requiresAlert": true,
      "date": "2027-08-06"
    },
    {
      "type": "HOLIDAY",
      "requiresAlert": false,
      "name": "Tish’a B’Av",
      "isSecondDay": false,
      "date": "2027-08-11",
      "id": "Tish’a_B’Av"
    },
    {
      "requiresAlert": true,
      "date": "2027-08-13",
      "name": "שבת פרשת ואתחנן",
      "id": "shabbat",
      "isSecondDay": false,
      "type": "SHABBAT"
    },
    {
      "name": "Tu B’Av",
      "type": "HOLIDAY",
      "date": "2027-08-17",
      "isSecondDay": false,
      "requiresAlert": false,
      "id": "Tu_B’Av"
    },
    {
      "requiresAlert": true,
      "isSecondDay": false,
      "id": "shabbat",
      "name": "שבת פרשת עקב",
      "type": "SHABBAT",
      "date": "2027-08-20"
    },
    {
      "requiresAlert": true,
      "type": "SHABBAT",
      "id": "shabbat",
      "name": "שבת פרשת ראה",
      "isSecondDay": false,
      "date": "2027-08-27"
    },
    {
      "name": "שבת פרשת שופטים",
      "date": "2027-09-03",
      "type": "SHABBAT",
      "isSecondDay": false,
      "id": "shabbat",
      "requiresAlert": true
    },
    {
      "type": "SHABBAT",
      "name": "שבת פרשת כי־תצא",
      "id": "shabbat",
      "date": "2027-09-10",
      "requiresAlert": true,
      "isSecondDay": false
    },
    {
      "date": "2027-09-17",
      "name": "שבת פרשת כי־תבוא",
      "id": "shabbat",
      "requiresAlert": true,
      "isSecondDay": false,
      "type": "SHABBAT"
    },
    {
      "name": "שבת פרשת נצבים-וילך",
      "id": "shabbat",
      "isSecondDay": false,
      "date": "2027-09-24",
      "requiresAlert": true,
      "type": "SHABBAT"
    },
    {
      "id": "שבת_-_ראש_השנה",
      "name": "שבת - ראש השנה",
      "requiresAlert": true,
      "isSecondDay": false,
      "date": "2027-10-01",
      "type": "HOLIDAY"
    },
    {
      "type": "HOLIDAY",
      "isSecondDay": true,
      "id": "ראש_השנה_(יום_ב')",
      "requiresAlert": false,
      "name": "ראש השנה (יום ב')",
      "date": "2027-10-02"
    },
    {
      "isSecondDay": false,
      "type": "SHABBAT",
      "date": "2027-10-08",
      "requiresAlert": true,
      "name": "שבת פרשת האזינו",
      "id": "shabbat"
    },
    {
      "type": "HOLIDAY",
      "requiresAlert": true,
      "name": "יום הכיפורים",
      "isSecondDay": false,
      "date": "2027-10-10",
      "id": "יום_הכיפורים"
    },
    {
      "name": "שבת - חג הסוכות",
      "isSecondDay": false,
      "id": "שבת_-_חג_הסוכות",
      "type": "HOLIDAY",
      "date": "2027-10-15",
      "requiresAlert": true
    },
    {
      "isSecondDay": false,
      "id": "Sukkot_II",
      "type": "HOLIDAY",
      "requiresAlert": false,
      "name": "Sukkot II",
      "date": "2027-10-16"
    },
    {
      "date": "2027-10-17",
      "name": "חול המועד סוכות",
      "type": "HOLIDAY",
      "isSecondDay": false,
      "requiresAlert": false,
      "id": "חול_המועד_סוכות"
    },
    {
      "type": "HOLIDAY",
      "isSecondDay": false,
      "name": "חול המועד סוכות",
      "requiresAlert": false,
      "id": "חול_המועד_סוכות",
      "date": "2027-10-18"
    },
    {
      "name": "חול המועד סוכות",
      "id": "חול_המועד_סוכות",
      "type": "HOLIDAY",
      "requiresAlert": false,
      "date": "2027-10-19",
      "isSecondDay": false
    },
    {
      "name": "חול המועד סוכות",
      "isSecondDay": false,
      "type": "HOLIDAY",
      "date": "2027-10-20",
      "id": "חול_המועד_סוכות",
      "requiresAlert": false
    },
    {
      "isSecondDay": false,
      "type": "HOLIDAY",
      "requiresAlert": false,
      "name": "Sukkot VII (Hoshana Raba)",
      "date": "2027-10-21",
      "id": "Sukkot_VII_(Hoshana_Raba)"
    },
    {
      "date": "2027-10-22",
      "isSecondDay": false,
      "type": "HOLIDAY",
      "id": "שבת_-_שמיני_עצרת_-_שמחת_תורה",
      "requiresAlert": true,
      "name": "שבת - שמיני עצרת - שמחת תורה"
    },
    {
      "name": "שמחת תורה",
      "requiresAlert": false,
      "isSecondDay": true,
      "type": "HOLIDAY",
      "date": "2027-10-23",
      "id": "שמחת_תורה"
    },
    {
      "date": "2027-10-29",
      "isSecondDay": false,
      "requiresAlert": true,
      "type": "SHABBAT",
      "id": "shabbat",
      "name": "שבת פרשת בראשית"
    },
    {
      "id": "shabbat",
      "type": "SHABBAT",
      "name": "שבת פרשת נח",
      "requiresAlert": true,
      "isSecondDay": false,
      "date": "2027-11-05"
    },
    {
      "id": "shabbat",
      "type": "SHABBAT",
      "name": "שבת פרשת לך־לך",
      "isSecondDay": false,
      "date": "2027-11-12",
      "requiresAlert": true
    },
    {
      "requiresAlert": true,
      "name": "שבת פרשת וירא",
      "id": "shabbat",
      "isSecondDay": false,
      "type": "SHABBAT",
      "date": "2027-11-19"
    },
    {
      "name": "שבת פרשת חיי שרה",
      "requiresAlert": true,
      "isSecondDay": false,
      "type": "SHABBAT",
      "date": "2027-11-26",
      "id": "shabbat"
    },
    {
      "isSecondDay": false,
      "requiresAlert": true,
      "type": "SHABBAT",
      "name": "שבת פרשת תולדות",
      "id": "shabbat",
      "date": "2027-12-03"
    },
    {
      "date": "2027-12-10",
      "name": "שבת פרשת ויצא",
      "isSecondDay": false,
      "type": "SHABBAT",
      "id": "shabbat",
      "requiresAlert": true
    },
    {
      "requiresAlert": true,
      "name": "שבת פרשת וישלח",
      "type": "SHABBAT",
      "date": "2027-12-17",
      "id": "shabbat",
      "isSecondDay": false
    },
    {
      "isSecondDay": false,
      "type": "HOLIDAY",
      "requiresAlert": false,
      "name": "חנוכה (נר ראשון)",
      "id": "חנוכה_(נר_ראשון)",
      "date": "2027-12-23"
    },
    {
      "name": "שבת פרשת וישב",
      "id": "shabbat",
      "date": "2027-12-24",
      "isSecondDay": false,
      "type": "SHABBAT",
      "requiresAlert": true
    },
    {
      "date": "2027-12-25",
      "type": "HOLIDAY",
      "requiresAlert": false,
      "id": "חנוכה",
      "name": "חנוכה",
      "isSecondDay": false
    },
    {
      "id": "חנוכה",
      "requiresAlert": false,
      "name": "חנוכה",
      "type": "HOLIDAY",
      "isSecondDay": false,
      "date": "2027-12-26"
    },
    {
      "requiresAlert": false,
      "isSecondDay": false,
      "id": "חנוכה",
      "name": "חנוכה",
      "date": "2027-12-27",
      "type": "HOLIDAY"
    },
    {
      "name": "חנוכה",
      "date": "2027-12-28",
      "isSecondDay": false,
      "id": "חנוכה",
      "type": "HOLIDAY",
      "requiresAlert": false
    },
    {
      "requiresAlert": false,
      "isSecondDay": false,
      "date": "2027-12-29",
      "name": "חנוכה",
      "type": "HOLIDAY",
      "id": "חנוכה"
    },
    {
      "requiresAlert": false,
      "name": "חנוכה",
      "id": "חנוכה",
      "date": "2027-12-30",
      "type": "HOLIDAY",
      "isSecondDay": false
    }
  ]
}