{
  "year": 2029,
  "events": [
    {
      "name": "שבת פרשת שמות",
      "requiresAlert": true,
      "date": "2029-01-05",
      "id": "shabbat",
      "isSecondDay": false,
      "type": "SHABBAT"
    },
    {
      "isSecondDay": false,
      "name": "שבת פרשת וארא",
      "requiresAlert": true,
      "type": "SHABBAT",
      "date": "2029-01-12",
      "id": "shabbat"
    },
    {
      "name": "שבת פרשת בא",
      "type": "SHABBAT",
      "date": "2029-01-19",
      "requiresAlert": true,
      "id": "shabbat",
      "isSecondDay": false
    },
    {
      "name": "שבת פרשת בשלח",
      "type": "SHABBAT",
      "date": "2029-01-26",
      "id": "shabbat",
      "isSecondDay": false,
      "requiresAlert": true
    },
    {
      "name": "ט\"ו בשבט",
      "requiresAlert": false,
      "date": "2029-01-30",
      "type": "HOLIDAY",
      "isSecondDay": false,
      "id": "ט\"ו_בשבט"
    },
    {
      "date": "2029-02-02",
      "id": "shabbat",
      "isSecondDay": false,
      "name": "שבת פרשת יתרו",
      "requiresAlert": true,
      "type": "SHABBAT"
    },
    {
      "name": "שבת פרשת משפטים",
      "id": "shabbat",
      "type": "SHABBAT",
      "requiresAlert": true,
      "isSecondDay": false,
      "date": "2029-02-09"
    },
    {
      "isSecondDay": false,
      "requiresAlert": true,
      "type": "SHABBAT",
      "date": "2029-02-16",
      "name": "שבת פרשת תרומה",
      "id": "shabbat"
    },
    {
      "id": "shabbat",
      "requiresAlert": true,
      "isSecondDay": false,
      "name": "שבת פרשת תצוה",
      "date": "2029-02-23",
      "type": "SHABBAT"
    },
    {
      "name": "פורים",
      "id": "פורים",
      "requiresAlert": false,
      "isSecondDay": false,
      "type": "HOLIDAY",
      "date": "2029-02-28"
    },
    {
      "name": "שושן פורים",
      "isSecondDay": false,
      "type": "HOLIDAY",
      "date": "2029-03-01",
      "id": "שושן_פורים",
      "requiresAlert": false
    },
    {
      "type": "SHABBAT",
      "date": "2029-03-02",
      "id": "shabbat",
      "requiresAlert": true,
      "isSecondDay": false,
      "name": "שבת פרשת כי תשא"
    },
    {
      "isSecondDay": false,
      "name": "שבת פרשת ויקהל-פקודי",
      "requiresAlert": true,
      "date": "2029-03-09",
      "id": "shabbat",
      "type": "SHABBAT"
    },
    {
      "requiresAlert": true,
      "date": "2029-03-16",
      "id": "shabbat",
      "type": "SHABBAT",
      "name": "שבת פרשת ויקרא",
      "isSecondDay": false
    },
    {
      "requiresAlert": true,
      "date": "2029-03-23",
      "type": "SHABBAT",
      "isSecondDay": false,
      "name": "שבת פרשת צו",
      "id": "shabbat"
    },
    {
      "isSecondDay": false,
      "requiresAlert": true,
      "id": "שבת_-_חג_הפסח_(ליל_הסדר)",
      "type": "HOLIDAY",
      "name": "שבת - חג הפסח (ליל הסדר)",
      "date": "2029-03-30"
    },
    {
      "date": "2029-03-31",
      "requiresAlert": false,
      "isSecondDay": false,
      "type": "HOLIDAY",
      "name": "Pesach II",
      "id": "Pesach_II"
    },
    {
      "isSecondDay": false,
      "name": "חול המועד פסח",
      "date": "2029-04-01",
      "id": "חול_המועד_פסח",
      "requiresAlert": false,
      "type": "HOLIDAY"
    },
    {
      "requiresAlert": false,
      "name": "חול המועד פסח",
      "id": "חול_המועד_פסח",
      "type": "HOLIDAY",
      "date": "2029-04-02",
      "isSecondDay": false
    },
    {
      "type": "HOLIDAY",
      "id": "חול_המועד_פסח",
      "date": "2029-04-03",
      "requiresAlert": false,
      "name": "חול המועד פסח",
      "isSecondDay": false
    },
    {
      "id": "חול_המועד_פסח",
      "date": "2029-04-04",
      "requiresAlert": false,
      "isSecondDay": false,
      "type": "HOLIDAY",
      "name": "חול המועד פסח"
    },
    {
      "requiresAlert": true,
      "id": "שביעי_של_פסח",
      "name": "שביעי של פסח",
      "date": "2029-04-05",
      "isSecondDay": false,
      "type": "HOLIDAY"
    },
    {
      "name": "שבת פרשת שמיני",
      "isSecondDay": false,
      "id": "shabbat",
      "requiresAlert": true,
      "date": "2029-04-13",
      "type": "SHABBAT"
    },
    {
      "date": "2029-04-20",
      "id": "shabbat",
      "isSecondDay": false,
      "name": "שבת פרשת תזריע-מצרע",
      "type": "SHABBAT",
      "requiresAlert": true
    },
    {
      "date": "2029-04-27",
      "requiresAlert": true,
      "id": "shabbat",
      "isSecondDay": false,
      "type": "SHABBAT",
      "name": "שבת פרשת אחרי מות-קדשים"
    },
    {
      "requiresAlert": true,
      "id": "shabbat",
      "name": "שבת פרשת אמור",
      "date": "2029-05-04",
      "type": "SHABBAT",
      "isSecondDay": false
    },
    {
      "type": "SHABBAT",
      "isSecondDay": false,
      "id": "shabbat",
      "name": "שבת פרשת בהר-בחקתי",
      "date": "2029-05-11",
      "requiresAlert": true
    },
    {
      "id": "shabbat",
      "date": "2029-05-18",
      "requiresAlert": true,
      "isSecondDay": false,
      "name": "שבת פרשת במדבר",
      "type": "SHABBAT"
    },
    {
      "type": "HOLIDAY",
      "date": "2029-05-19",
      "requiresAlert": false,
      "isSecondDay": true,
      "name": "חג השבועות",
      "id": "חג_השבועות"
    },
    {
      "requiresAlert": false,
      "id": "Shavuot_II",
      "isSecondDay": false,
      "date": "2029-05-20",
      "name": "Shavuot II",
      "type": "HOLIDAY"
    },
    {
      "requiresAlert": true,
      "date": "2029-05-25",
      "isSecondDay": false,
      "type": "SHABBAT",
      "name": "שבת פרשת נשא",
      "id": "shabbat"
    },
    {
      "requiresAlert": true,
      "type": "SHABBAT",
      "date": "2029-06-01",
      "id": "shabbat",
      "name": "שבת פרשת בהעלתך",
      "isSecondDay": false
    },
    {
      "type": "SHABBAT",
      "id": "shabbat",
      "date": "2029-06-08",
      "requiresAlert": true,
      "name": "שבת פרשת שלח־לך",
      "isSecondDay": false
    },
    {
      "name": "שבת פרשת קורח",
      "date": "2029-06-15",
      "requiresAlert": true,
      "type": "SHABBAT",
      "isSecondDay": false,
      "id": "shabbat"
    },
    {
      "date": "2029-06-22",
      "name": "שבת פרשת חוקת",
      "type": "SHABBAT",
      "requiresAlert": true,
      "isSecondDay": false,
      "id": "shabbat"
    },
    {
      "name": "שבת פרשת בלק",
      "requiresAlert": true,
      "type": "SHABBAT",
      "date": "2029-06-29",
      "isSecondDay": false,
      "id": "shabbat"
    },
    {
      "requiresAlert": true,
      "date": "2029-07-06",
      "type": "SHABBAT",
      "id": "shabbat",
      "isSecondDay": false,
      "name": "שבת פרשת פינחס"
    },
    {
      "isSecondDay": false,
      "name": "שבת פרשת מטות-מסעי",
      "requiresAlert": true,
      "type": "SHABBAT",
      "date": "2029-07-13",
      "id": "shabbat"
    },
    {
      "isSecondDay": false,
      "name": "שבת פרשת דברים",
      "requiresAlert": true,
      "type": "SHABBAT",
      "date": "2029-07-20",
      "id": "shabbat"
    },
    {
      "name": "Tish’a B’Av (observed)",
      "requiresAlert": false,
      "date": "2029-07-21",
      "id": "Tish’a_B’Av_(observed)",
      "type": "HOLIDAY",
      "isSecondDay": false
    },
    {
      "name": "Tu B’Av",
      "type": "HOLIDAY",
      "date": "2029-07-26",
      "requiresAlert": false,
      "isSecondDay": false,
      "id": "Tu_B’Av"
    },
    {
      "name": "שבת פרשת ואתחנן",
      "type": "SHABBAT",
      "id": "shabbat",
      "isSecondDay": false,
      "requiresAlert": true,
      "date": "2029-07-27"
    },
    {
      "type": "SHABBAT",
      "date": "2029-08-03",
      "id": "shabbat",
      "isSecondDay": false,
      "name": "שבת פרשת עקב",
      "requiresAlert": true
    },
    {
      "date": "2029-08-10",
      "isSecondDay": false,
      "requiresAlert": true,
      "type": "SHABBAT",
      "name": "שבת פרשת ראה",
      "id": "shabbat"
    },
    {
      "name": "שבת פרשת שופטים",
      "type": "SHABBAT",
      "isSecondDay": false,
      "requiresAlert": true,
      "id": "shabbat",
      "date": "2029-08-17"
    },
    {
      "date": "2029-08-24",
      "id": "shabbat",
      "name": "שבת פרשת כי־תצא",
      "type": "SHABBAT",
      "isSecondDay": false,
      "requiresAlert": true
    },
    {
      "requiresAlert": true,
      "isSecondDay": false,
      "type": "SHABBAT",
      "date": "2029-08-31",
      "id": "shabbat",
      "name": "שבת פרשת כי־תבוא"
    },
    {
      "requiresAlert": true,
      "type": "SHABBAT",
      "id": "shabbat",
      "date": "2029-09-07",
      "isSecondDay": false,
      "name": "שבת פרשת נצבים"
    },
    {
      "date": "2029-09-09",
      "type": "HOLIDAY",
      "id": "ראש_השנה",
      "requiresAlert": true,
      "name": "ראש השנה",
      "isSecondDay": false
    },
    {
      "name": "ראש השנה (יום ב')",
      "isSecondDay": true,
      "type": "HOLIDAY",
      "date": "2029-09-10",
      "id": "ראש_השנה_(יום_ב')",
      "requiresAlert": false
    },
    {
      "requiresAlert": true,
      "type": "SHABBAT",
      "isSecondDay": false,
      "name": "שבת פרשת וילך",
      "date": "2029-09-14",
      "id": "shabbat"
    },
    {
      "name": "יום הכיפורים",
      "id": "יום_הכיפורים",
      "date": "2029-09-18",
      "isSecondDay": false,
      "type": "HOLIDAY",
      "requiresAlert": true
    },
    {
      "isSecondDay": false,
      "name": "שבת פרשת האזינו",
      "type": "SHABBAT",
      "requiresAlert": true,
      "date": "2029-09-21",
      "id": "shabbat"
    },
    {
      "date": "2029-09-23",
      "name": "חג הסוכות",
      "type": "HOLIDAY",
      "isSecondDay": false,
      "id": "חג_הסוכות",
      "requiresAlert": true
    },
    {
      "date": "2029-09-24",
      "type": "HOLIDAY",
      "isSecondDay": false,
      "requiresAlert": false,
      "id": "Sukkot_II",
      "name": "Sukkot II"
    },
    {
      "requiresAlert": false,
      "id": "חול_המועד_סוכות",
      "type": "HOLIDAY",
      "isSecondDay": false,
      "date": "2029-09-25",
      "name": "חול המועד סוכות"
    },
    {
      "date": "2029-09-26",
      "name": "חול המועד סוכות",
      "isSecondDay": false,
      "id": "חול_המועד_סוכות",
      "requiresAlert": false,
      "type": "HOLIDAY"
    },
    {
      "type": "HOLIDAY",
      "name": "חול המועד סוכות",
      "date": "2029-09-27",
      "isSecondDay": false,
      "id": "חול_המועד_סוכות",
      "requiresAlert": false
    },
    {
      "id": "שבת_-_חול_המועד_סוכות",
      "requiresAlert": true,
      "isSecondDay": false,
      "name": "שבת - חול המועד סוכות",
      "date": "2029-09-28",
      "type": "HOLIDAY"
    },
    {
      "isSecondDay": false,
      "date": "2029-09-29",
      "requiresAlert": false,
      "name": "Sukkot VII (Hoshana Raba)",
      "id": "Sukkot_VII_(Hoshana_Raba)",
      "type": "HOLIDAY"
    },
    {
      "type": "HOLIDAY",
      "date": "2029-09-30",
      "requiresAlert": true,
      "isSecondDay": false,
      "id": "שמיני_עצרת_-_שמחת_תורה",
      "name": "שמיני עצרת - שמחת תורה"
    },
    {
      "date": "2029-10-01",
      "name": "שמחת תורה",
      "type": "HOLIDAY",
      "id": "שמחת_תורה",
      "requiresAlert": false,
      "isSecondDay": true
    },
    {
      "type": "SHABBAT",
      "date": "2029-10-05",
      "id": "shabbat",
      "name": "שבת פרשת בראשית",
      "requiresAlert": true,
      "isSecondDay": false
    },
    {
      "date": "2029-10-12",
      "name": "שבת פרשת נח",
      "type": "SHABBAT",
      "requiresAlert": true,
      "isSecondDay": false,
      "id": "shabbat"
    },
    {
      "requiresAlert": true,
      "id": "shabbat",
      "date": "2029-10-19",
      "isSecondDay": false,
      "type": "SHABBAT",
      "name": "שבת פרשת לך־לך"
    },
    {
      "id": "shabbat",
      "isSecondDay": false,
      "name": "שבת פרשת וירא",
      "type": "SHABBAT",
      "date": "2029-10-26",
      "requiresAlert": true
    },
    {
      "name": "שבת פרשת חיי שרה",
      "type": "SHABBAT",
      "date": "2029-11-02",
      "requiresAlert": true,
      "isSecondDay": false,
      "id": "shabbat"
    },
    {
      "id": "shabbat",
      "name": "שבת פרשת תולדות",
      "type": "SHABBAT",
      "isSecondDay": false,
      "requiresAlert": true,
      "date": "2029-11-09"
    },
    {
      "type": "SHABBAT",
      "isSecondDay": false,
      "requiresAlert": true,
      "id": "shabbat",
      "date": "2029-11-16",
      "name": "שבת פרשת ויצא"
    },
    {
      "requiresAlert": true,
      "type": "SHABBAT",
      "date": "2029-11-23",
      "id": "shabbat",
      "isSecondDay": false,
      "name": "שבת פרשת וישלח"
    },
    {
      "date": "2029-11-30",
      "id": "shabbat",
      "requiresAlert": true,
      "name": "שבת פרשת וישב",
      "type": "SHABBAT",
      "isSecondDay": false
    },
    {
      "type": "HOLIDAY",
      "name": "חנוכה",
      "date": "2029-12-01",
      "id": "חנוכה",
      "requiresAlert": false,
      "isSecondDay": false
    },
    {
      "date": "2029-12-02",
      "type": "HOLIDAY",
      "name": "חנוכה",
      "isSecondDay": false,
      "id": "חנוכה",
      "requiresAlert": false
    },
    {
      "date": "2029-12-03",
      "requiresAlert": false,
      "type": "HOLIDAY",
      "isSecondDay": false,
      "name": "חנוכה",
      "id": "חנוכה"
    },
    {
      "date": "2029-12-04",
      "isSecondDay": false,
      "requiresAlert": false,
      "id": "חנוכה",
      "type": "HOLIDAY",
      "name": "חנוכה"
    },
    {
      "id": "חנוכה",
      "isSecondDay": false,
      "date": "2029-12-05",
      "type": "HOLIDAY",
      "requiresAlert": false,
      "name": "חנוכה"
    },
    {
      "id": "חנוכה",
      "name": "חנוכה",
      "date": "2029-12-06",
      "requiresAlert": false,
      "isSecondDay": false,
      "type": "HOLIDAY"
    },
    {
      "date": "2029-12-07",
      "id": "shabbat",
      "isSecondDay": false,
      "type": "SHABBAT",
      "requiresAlert": true,
      "name": "שבת פרשת מקץ"
    },
    {
      "requiresAlert": false,
      "date": "2029-12-08",
      "name": "חנוכה",
      "id": "חנוכה",
      "isSecondDay": false,
      "type": "HOLIDAY"
    },
    {
      "requiresAlert": true,
      "isSecondDay": false,
      "type": "SHABBAT",
      "id": "shabbat",
      "name": "שבת פרשת ויגש",
      "date": "2029-12-14"
    },
    {
      "requiresAlert": true,
      "type": "SHABBAT",
      "isSecondDay": false,
      "id": "shabbat",
      "date": "2029-12-21",
      "name": "שבת פרשת ויחי"
    },
    {
      "id": "shabbat",
      "type": "SHABBAT",
      "name": "שבת פרשת שמות",
      "date": "2029-12-28",
      "requiresAlert": true,
      "isSecondDay": false
    }
  ],
  "updatedAt": "2025-12-14T13:17:56.891Z"
}