{
  "year": 2031,
  "events": [
    {
      "id": "shabbat",
      "name": "שבת פרשת ויגש",
      "isSecondDay": false,
      "date": "2031-01-03",
      "requiresAlert": true,
      "type": "SHABBAT"
    },
    {
      "name": "שבת פרשת ויחי",
      "date": "2031-01-10",
      "requiresAlert": true,
      "type": "SHABBAT",
      "isSecondDay": false,
      "id": "shabbat"
    },
    {
      "date": "2031-01-17",
      "name": "שבת פרשת שמות",
      "id": "shabbat",
      "isSecondDay": false,
      "requiresAlert": true,
      "type": "SHABBAT"
    },
    {
      "requiresAlert": true,
      "id": "shabbat",
      "isSecondDay": false,
      "type": "SHABBAT",
      "name": "שבת פרשת וארא",
      "date": "2031-01-24"
    },
    {
      "name": "שבת פרשת בא",
      "type": "SHABBAT",
      "requiresAlert": true,
      "id": "shabbat",
      "date": "2031-01-31",
      "isSecondDay": false
    },
    {
      "isSecondDay": false,
      "requiresAlert": true,
      "type": "SHABBAT",
      "date": "2031-02-07",
      "id": "shabbat",
      "name": "שבת פרשת בשלח"
    },
    {
      "isSecondDay": false,
      "name": "שבת פרשת יתרו",
      "type": "SHABBAT",
      "requiresAlert": true,
      "id": "shabbat",
      "date": "2031-02-14"
    },
    {
      "requiresAlert": true,
      "type": "SHABBAT",
      "id": "shabbat",
      "name": "שבת פרשת משפטים",
      "date": "2031-02-21",
      "isSecondDay": false
    },
    {
      "requiresAlert": true,
      "type": "SHABBAT",
      "date": "2031-02-28",
      "isSecondDay": false,
      "id": "shabbat",
      "name": "שבת פרשת תרומה"
    },
    {
      "name": "שבת פרשת תצוה",
      "date": "2031-03-07",
      "requiresAlert": true,
      "type": "SHABBAT",
      "isSecondDay": false,
      "id": "shabbat"
    },
    {
      "id": "פורים",
      "date": "2031-03-08",
      "requiresAlert": false,
      "isSecondDay": false,
      "type": "HOLIDAY",
      "name": "פורים"
    },
    {
      "type": "HOLIDAY",
      "name": "שושן פורים",
      "date": "2031-03-09",
      "isSecondDay": false,
      "id": "שושן_פורים",
      "requiresAlert": false
    },
    {
      "name": "שבת פרשת כי תשא",
      "id": "shabbat",
      "date": "2031-03-14",
      "isSecondDay": false,
      "type": "SHABBAT",
      "requiresAlert": true
    },
    {
      "date": "2031-03-21",
      "name": "שבת פרשת ויקהל-פקודי",
      "requiresAlert": true,
      "type": "SHABBAT",
      "isSecondDay": false,
      "id": "shabbat"
    },
    {
      "type": "SHABBAT",
      "id": "shabbat",
      "date": "2031-03-28",
      "isSecondDay": false,
      "requiresAlert": true,
      "name": "שבת פרשת ויקרא"
    },
    {
      "date": "2031-04-04",
      "id": "shabbat",
      "requiresAlert": true,
      "name": "שבת פרשת צו",
      "type": "SHABBAT",
      "isSecondDay": false
    },
    {
      "requiresAlert": true,
      "id": "חג_הפסח_(ליל_הסדר)",
      "type": "HOLIDAY",
      "name": "חג הפסח (ליל הסדר)",
      "isSecondDay": false,
      "date": "2031-04-07"
    },
    {
      "type": "HOLIDAY",
      "requiresAlert": false,
      "date": "2031-04-08",
      "name": "Pesach II",
      "id": "Pesach_II",
      "isSecondDay": false
    },
    {
      "name": "חול המועד פסח",
      "requiresAlert": false,
      "id": "חול_המועד_פסח",
      "isSecondDay": false,
      "date": "2031-04-09",
      "type": "HOLIDAY"
    },
    {
      "requiresAlert": false,
      "id": "חול_המועד_פסח",
      "type": "HOLIDAY",
      "isSecondDay": false,
      "date": "2031-04-10",
      "name": "חול המועד פסח"
    },
    {
      "date": "2031-04-11",
      "name": "שבת - חול המועד פסח",
      "id": "שבת_-_חול_המועד_פסח",
      "requiresAlert": true,
      "isSecondDay": false,
      "type": "HOLIDAY"
    },
    {
      "date": "2031-04-12",
      "id": "חול_המועד_פסח",
      "name": "חול המועד פסח",
      "isSecondDay": false,
      "requiresAlert": false,
      "type": "HOLIDAY"
    },
    {
      "date": "2031-04-13",
      "requiresAlert": true,
      "type": "HOLIDAY",
      "name": "שביעי של פסח",
      "isSecondDay": false,
      "id": "שביעי_של_פסח"
    },
    {
      "isSecondDay": false,
      "name": "שבת פרשת שמיני",
      "id": "shabbat",
      "date": "2031-04-18",
      "requiresAlert": true,
      "type": "SHABBAT"
    },
    {
      "name": "שבת פרשת תזריע-מצרע",
      "date": "2031-04-25",
      "requiresAlert": true,
      "id": "shabbat",
      "type": "SHABBAT",
      "isSecondDay": false
    },
    {
      "date": "2031-05-02",
      "name": "שבת פרשת אחרי מות-קדשים",
      "isSecondDay": false,
      "requiresAlert": true,
      "type": "SHABBAT",
      "id": "shabbat"
    },
    {
      "requiresAlert": true,
      "date": "2031-05-09",
      "id": "shabbat",
      "type": "SHABBAT",
      "name": "שבת פרשת אמור",
      "isSecondDay": false
    },
    {
      "type": "SHABBAT",
      "date": "2031-05-16",
      "isSecondDay": false,
      "name": "שבת פרשת בהר-בחקתי",
      "requiresAlert": true,
      "id": "shabbat"
    },
    {
      "requiresAlert": true,
      "name": "שבת פרשת במדבר",
      "id": "shabbat",
      "type": "SHABBAT",
      "date": "2031-05-23",
      "isSecondDay": false
    },
    {
      "isSecondDay": false,
      "type": "HOLIDAY",
      "id": "חג_השבועות",
      "date": "2031-05-27",
      "name": "חג השבועות",
      "requiresAlert": true
    },
    {
      "requiresAlert": false,
      "id": "Shavuot_II",
      "date": "2031-05-28",
      "type": "HOLIDAY",
      "name": "Shavuot II",
      "isSecondDay": false
    },
    {
      "date": "2031-05-30",
      "type": "SHABBAT",
      "requiresAlert": true,
      "name": "שבת פרשת נשא",
      "id": "shabbat",
      "isSecondDay": false
    },
    {
      "id": "shabbat",
      "date": "2031-06-06",
      "requiresAlert": true,
      "type": "SHABBAT",
      "isSecondDay": false,
      "name": "שבת פרשת בהעלתך"
    },
    {
      "date": "2031-06-13",
      "type": "SHABBAT",
      "name": "שבת פרשת שלח־לך",
      "requiresAlert": true,
      "isSecondDay": false,
      "id": "shabbat"
    },
    {
      "requiresAlert": true,
      "type": "SHABBAT",
      "name": "שבת פרשת קורח",
      "isSecondDay": false,
      "id": "shabbat",
      "date": "2031-06-20"
    },
    {
      "id": "shabbat",
      "type": "SHABBAT",
      "isSecondDay": false,
      "name": "שבת פרשת חוקת",
      "date": "2031-06-27",
      "requiresAlert": true
    },
    {
      "id": "shabbat",
      "type": "SHABBAT",
      "name": "שבת פרשת בלק",
      "date": "2031-07-04",
      "requiresAlert": true,
      "isSecondDay": false
    },
    {
      "name": "שבת פרשת פינחס",
      "requiresAlert": true,
      "isSecondDay": false,
      "date": "2031-07-11",
      "type": "SHABBAT",
      "id": "shabbat"
    },
    {
      "isSecondDay": false,
      "id": "shabbat",
      "type": "SHABBAT",
      "requiresAlert": true,
      "name": "שבת פרשת מטות-מסעי",
      "date": "2031-07-18"
    },
    {
      "isSecondDay": false,
      "date": "2031-07-25",
      "name": "שבת פרשת דברים",
      "type": "SHABBAT",
      "id": "shabbat",
      "requiresAlert": true
    },
    {
      "requiresAlert": false,
      "type": "HOLIDAY",
      "isSecondDay": false,
      "name": "Tish’a B’Av",
      "id": "Tish’a_B’Av",
      "date": "2031-07-28"
    },
    {
      "isSecondDay": false,
      "id": "shabbat",
      "type": "SHABBAT",
      "requiresAlert": true,
      "name": "שבת פרשת ואתחנן",
      "date": "2031-08-01"
    },
    {
      "isSecondDay": false,
      "type": "HOLIDAY",
      "id": "Tu_B’Av",
      "date": "2031-08-03",
      "name": "Tu B’Av",
      "requiresAlert": false
    },
    {
      "requiresAlert": true,
      "isSecondDay": false,
      "type": "SHABBAT",
      "id": "shabbat",
      "date": "2031-08-08",
      "name": "שבת פרשת עקב"
    },
    {
      "name": "שבת פרשת ראה",
      "id": "shabbat",
      "isSecondDay": false,
      "type": "SHABBAT",
      "date": "2031-08-15",
      "requiresAlert": true
    },
    {
      "date": "2031-08-22",
      "requiresAlert": true,
      "isSecondDay": false,
      "id": "shabbat",
      "name": "שבת פרשת שופטים",
      "type": "SHABBAT"
    },
    {
      "requiresAlert": true,
      "name": "שבת פרשת כי־תצא",
      "date": "2031-08-29",
      "id": "shabbat",
      "isSecondDay": false,
      "type": "SHABBAT"
    },
    {
      "date": "2031-09-05",
      "type": "SHABBAT",
      "requiresAlert": true,
      "id": "shabbat",
      "isSecondDay": false,
      "name": "שבת פרשת כי־תבוא"
    },
    {
      "name": "שבת פרשת נצבים-וילך",
      "requiresAlert": true,
      "isSecondDay": false,
      "id": "shabbat",
      "type": "SHABBAT",
      "date": "2031-09-12"
    },
    {
      "id": "ראש_השנה",
      "name": "ראש השנה",
      "isSecondDay": false,
      "requiresAlert": true,
      "date": "2031-09-17",
      "type": "HOLIDAY"
    },
    {
      "type": "HOLIDAY",
      "date": "2031-09-18",
      "name": "ראש השנה (יום ב')",
      "id": "ראש_השנה_(יום_ב')",
      "requiresAlert": false,
      "isSecondDay": true
    },
    {
      "type": "SHABBAT",
      "name": "שבת פרשת האזינו",
      "id": "shabbat",
      "isSecondDay": false,
      "date": "2031-09-19",
      "requiresAlert": true
    },
    {
      "type": "HOLIDAY",
      "id": "שבת_-_יום_הכיפורים",
      "requiresAlert": true,
      "isSecondDay": false,
      "date": "2031-09-26",
      "name": "שבת - יום הכיפורים"
    },
    {
      "name": "חג הסוכות",
      "id": "חג_הסוכות",
      "requiresAlert": true,
      "isSecondDay": false,
      "type": "HOLIDAY",
      "date": "2031-10-01"
    },
    {
      "id": "Sukkot_II",
      "isSecondDay": false,
      "name": "Sukkot II",
      "date": "2031-10-02",
      "requiresAlert": false,
      "type": "HOLIDAY"
    },
    {
      "requiresAlert": true,
      "isSecondDay": false,
      "id": "שבת_-_חול_המועד_סוכות",
      "date": "2031-10-03",
      "type": "HOLIDAY",
      "name": "שבת - חול המועד סוכות"
    },
    {
      "name": "חול המועד סוכות",
      "isSecondDay": false,
      "requiresAlert": false,
      "type": "HOLIDAY",
      "id": "חול_המועד_סוכות",
      "date": "2031-10-04"
    },
    {
      "name": "חול המועד סוכות",
      "requiresAlert": false,
      "type": "HOLIDAY",
      "date": "2031-10-05",
      "isSecondDay": false,
      "id": "חול_המועד_סוכות"
    },
    {
      "type": "HOLIDAY",
      "id": "חול_המועד_סוכות",
      "name": "חול המועד סוכות",
      "date": "2031-10-06",
      "isSecondDay": false,
      "requiresAlert": false
    },
    {
      "name": "Sukkot VII (Hoshana Raba)",
      "id": "Sukkot_VII_(Hoshana_Raba)",
      "date": "2031-10-07",
      "requiresAlert": false,
      "isSecondDay": false,
      "type": "HOLIDAY"
    },
    {
      "date": "2031-10-08",
      "type": "HOLIDAY",
      "isSecondDay": false,
      "name": "שמיני עצרת - שמחת תורה",
      "id": "שמיני_עצרת_-_שמחת_תורה",
      "requiresAlert": true
    },
    {
      "requiresAlert": false,
      "type": "HOLIDAY",
      "date": "2031-10-09",
      "name": "שמחת תורה",
      "isSecondDay": true,
      "id": "שמחת_תורה"
    },
    {
      "isSecondDay": false,
      "requiresAlert": true,
      "id": "shabbat",
      "type": "SHABBAT",
      "date": "2031-10-10",
      "name": "שבת פרשת בראשית"
    },
    {
      "id": "shabbat",
      "date": "2031-10-17",
      "isSecondDay": false,
      "type": "SHABBAT",
      "name": "שבת פרשת נח",
      "requiresAlert": true
    },
    {
      "isSecondDay": false,
      "date": "2031-10-24",
      "name": "שבת פרשת לך־לך",
      "id": "shabbat",
      "requiresAlert": true,
      "type": "SHABBAT"
    },
    {
      "type": "SHABBAT",
      "id": "shabbat",
      "date": "2031-10-31",
      "name": "שבת פרשת וירא",
      "requiresAlert": true,
      "isSecondDay": false
    },
    {
      "type": "SHABBAT",
      "isSecondDay": false,
      "id": "shabbat",
      "date": "2031-11-07",
      "name": "שבת פרשת חיי שרה",
      "requiresAlert": true
    },
    {
      "type": "SHABBAT",
      "name": "שבת פרשת תולדות",
      "id": "shabbat",
      "requiresAlert": true,
      "date": "2031-11-14",
      "isSecondDay": false
    },
    {
      "date": "2031-11-21",
      "name": "שבת פרשת ויצא",
      "id": "shabbat",
      "type": "SHABBAT",
      "isSecondDay": false,
      "requiresAlert": true
    },
    {
      "isSecondDay": false,
      "requiresAlert": true,
      "id": "shabbat",
      "date": "2031-11-28",
      "name": "שבת פרשת וישלח",
      "type": "SHABBAT"
    },
    {
      "date": "2031-12-05",
      "id": "shabbat",
      "type": "SHABBAT",
      "requiresAlert": true,
      "name": "שבת פרשת וישב",
      "isSecondDay": false
    },
    {
      "id": "חנוכה_(נר_ראשון)",
      "name": "חנוכה (נר ראשון)",
      "type": "HOLIDAY",
      "requiresAlert": false,
      "date": "2031-12-08",
      "isSecondDay": false
    },
    {
      "isSecondDay": false,
      "date": "2031-12-09",
      "id": "חנוכה",
      "requiresAlert": false,
      "name": "חנוכה",
      "type": "HOLIDAY"
    },
    {
      "name": "חנוכה",
      "id": "חנוכה",
      "type": "HOLIDAY",
      "date": "2031-12-10",
      "isSecondDay": false,
      "requiresAlert": false
    },
    {
      "type": "HOLIDAY",
      "date": "2031-12-11",
      "isSecondDay": false,
      "name": "חנוכה",
      "requiresAlert": false,
      "id": "חנוכה"
    },
    {
      "name": "שבת פרשת מקץ",
      "type": "SHABBAT",
      "id": "shabbat",
      "isSecondDay": false,
      "date": "2031-12-12",
      "requiresAlert": true
    },
    {
      "id": "חנוכה",
      "isSecondDay": false,
      "type": "HOLIDAY",
      "date": "2031-12-13",
      "name": "חנוכה",
      "requiresAlert": false
    },
    {
      "date": "2031-12-14",
      "id": "חנוכה",
      "type": "HOLIDAY",
      "requiresAlert": false,
      "name": "חנוכה",
      "isSecondDay": false
    },
    {
      "id": "חנוכה",
      "type": "HOLIDAY",
      "date": "2031-12-15",
      "isSecondDay": false,
      "requiresAlert": false,
      "name": "חנוכה"
    },
    {
      "requiresAlert": false,
      "isSecondDay": false,
      "type": "HOLIDAY",
      "date": "2031-12-16",
      "name": "חנוכה",
      "id": "חנוכה"
    },
    {
      "requiresAlert": true,
      "type": "SHABBAT",
      "id": "shabbat",
      "isSecondDay": false,
      "name": "שבת פרשת ויגש",
      "date": "2031-12-19"
    },
    {
      "type": "SHABBAT",
      "name": "שבת פרשת ויחי",
      "isSecondDay": false,
      "requiresAlert": true,
      "id": "shabbat",
      "date": "2031-12-26"
    }
  ],
  "updatedAt": "2025-12-22T14:52:04.989Z"
}